MANIFEST.in
README.md
setup.py
guillotina_gmi/__init__.py
guillotina_gmi.egg-info/PKG-INFO
guillotina_gmi.egg-info/SOURCES.txt
guillotina_gmi.egg-info/dependency_links.txt
guillotina_gmi.egg-info/not-zip-safe
guillotina_gmi.egg-info/requires.txt
guillotina_gmi.egg-info/top_level.txt
guillotina_gmi/__pycache__/__init__.cpython-38.pyc
guillotina_gmi/gmi/asset-manifest.json
guillotina_gmi/gmi/favicon.ico
guillotina_gmi/gmi/index.html
guillotina_gmi/gmi/logo.svg
guillotina_gmi/gmi/logo512.png
guillotina_gmi/gmi/manifest.json
guillotina_gmi/gmi/robots.txt
guillotina_gmi/gmi/static/css/main.46d504b1.chunk.css
guillotina_gmi/gmi/static/css/main.46d504b1.chunk.css.map
guillotina_gmi/gmi/static/js/2.75355bd4.chunk.js
guillotina_gmi/gmi/static/js/2.75355bd4.chunk.js.LICENSE.txt
guillotina_gmi/gmi/static/js/2.75355bd4.chunk.js.map
guillotina_gmi/gmi/static/js/3.6bd5101d.chunk.js
guillotina_gmi/gmi/static/js/3.6bd5101d.chunk.js.map
guillotina_gmi/gmi/static/js/main.6fbad553.chunk.js
guillotina_gmi/gmi/static/js/main.6fbad553.chunk.js.map
guillotina_gmi/gmi/static/js/runtime-main.ed007052.js
guillotina_gmi/gmi/static/js/runtime-main.ed007052.js.map