Metadata-Version: 2.1
Name: guillotina-gmi
Version: 0.1.0
Summary: guillotina management interface
Home-page: https://github.com/guillotinaweb/guillotina_react
Author: jordi collell
Author-email: jordic@gmail.com
License: BSD
Keywords: guillotina_gmi,zmi,gmi
Platform: UNKNOWN
Classifier: License :: OSI Approved :: BSD License
Classifier: Intended Audience :: Developers
Classifier: Topic :: Internet :: WWW/HTTP
Classifier: Programming Language :: Python :: 3.7
Classifier: Programming Language :: Python :: 3.8
Classifier: Topic :: Software Development :: Libraries :: Python Modules
Requires-Python: >=3.7.0
Provides-Extra: dev
